pyrobox/__init__.py
pyrobox/__main__.py
pyrobox/_arg_parser.py
pyrobox/_exceptions.py
pyrobox/_fs_utils.py
pyrobox/_list_maker.py
pyrobox/_page_templates.py
pyrobox/_sub_extractor.py
pyrobox/_zipfly_manager.py
pyrobox/clone.py
pyrobox/data_types.py
pyrobox/pyroDB.py
pyrobox/pyroboxCore.py
pyrobox/pyrobox_ServerHost.py
pyrobox/server.py
pyrobox/tools.py
pyrobox/user_mgmt.py
pyrobox-0.9.9.dist-info/LICENSE
pyrobox-0.9.9.dist-info/METADATA
pyrobox-0.9.9.dist-info/WHEEL
pyrobox-0.9.9.dist-info/entry_points.txt
pyrobox-0.9.9.dist-info/top_level.txt
pyrobox-0.9.9.dist-info/RECORD
