Metadata-Version: 2.2
Name: pyrobox
Version: 0.9.9
Summary: Personal DropBox for Private Network
Home-page: https://github.com/RaSan147/pyrobox
Author: Rasan
Author-email: wwwqweasd147@gmail.com
Project-URL: Bug Tracker, https://github.com/RaSan147/pyrobox/issues
Project-URL: Documentation, https://github.com/RaSan147/pyrobox
Project-URL: Source Code, https://github.com/RaSan147/pyrobox
Project-URL: Release Notes, https://github.com/RaSan147/pyrobox/releases
Classifier: Programming Language :: Python :: 3.7
Classifier: Programming Language :: Python :: 3.8
Classifier: Programming Language :: Python :: 3.9
Classifier: Programming Language :: Python :: 3.10
Classifier: Programming Language :: Python :: 3.11
Classifier: Programming Language :: Python :: 3.12
Classifier: Programming Language :: Python :: 3.13
Classifier: License :: OSI Approved :: MIT License
Classifier: Operating System :: OS Independent
Classifier: Topic :: Internet :: File Transfer Protocol (FTP)
Classifier: Topic :: Communications :: File Sharing
Requires-Python: >=3.7
License-File: LICENSE
Requires-Dist: natsort
Requires-Dist: send2trash
Requires-Dist: msgpack
Requires-Dist: tabulate2
Requires-Dist: pyqrcode
Requires-Dist: requests
Dynamic: requires-dist
